cstruct/__init__.py
cstruct/abstract.py
cstruct/base.py
cstruct/c_expr.py
cstruct/c_parser.py
cstruct/cenum.py
cstruct/cstruct.py
cstruct/exceptions.py
cstruct/field.py
cstruct/mem_cstruct.py
cstruct/native_types.py
cstruct-6.1.dist-info/licenses/LICENSE
cstruct-6.1.dist-info/METADATA
cstruct-6.1.dist-info/WHEEL
cstruct-6.1.dist-info/top_level.txt
cstruct-6.1.dist-info/zip-safe
cstruct-6.1.dist-info/RECORD
